json_to_csv_lol/__init__.py
json_to_csv_lol/__main__.py
json_to_csv_lol/converter.py
json_to_csv_lol/main.py
json_to_csv_lol-0.1.1.dist-info/entry_points.txt
json_to_csv_lol-0.1.1.dist-info/WHEEL
json_to_csv_lol-0.1.1.dist-info/METADATA
json_to_csv_lol-0.1.1.dist-info/RECORD
